yaml_extensions/__init__.py
yaml_extensions/inclusions.py
yaml_extensions-0.0.2.dist-info/LICENSE
yaml_extensions-0.0.2.dist-info/METADATA
yaml_extensions-0.0.2.dist-info/WHEEL
yaml_extensions-0.0.2.dist-info/top_level.txt
yaml_extensions-0.0.2.dist-info/RECORD
