Metadata-Version: 2.1
Name: yaml-extensions
Version: 0.0.2
Author-email: "Phil Weir obo. Carl Zeiss AG" <phil.weir.ext@zeiss.com>
License: Apache License
Requires-Python: >=3.9
License-File: LICENSE
Requires-Dist: pyyaml (~=6.0)
Provides-Extra: test
Requires-Dist: pytest (>=7) ; extra == 'test'
Requires-Dist: black (>=21) ; extra == 'test'
Requires-Dist: flake8 ; extra == 'test'
